icoexpnet/__init__.py
icoexpnet/analysis/ExperimentSet.py
icoexpnet/analysis/GraphHelper.py
icoexpnet/analysis/GraphToolExp.py
icoexpnet/analysis/NetworkComp.py
icoexpnet/analysis/NetworkOutput.py
icoexpnet/analysis/__init__.py
icoexpnet/analysis/utilities/__init__.py
icoexpnet/analysis/utilities/clustering.py
icoexpnet/analysis/utilities/helpers.py
icoexpnet/analysis/utilities/pre_processing.py
icoexpnet/analysis/utilities/sankey_consensus_plot.py
icoexpnet/core/__init__.py
icoexpnet/core/main.py
icoexpnet-0.1.12.dist-info/licenses/LICENSE
icoexpnet-0.1.12.dist-info/METADATA
icoexpnet-0.1.12.dist-info/WHEEL
icoexpnet-0.1.12.dist-info/top_level.txt
icoexpnet-0.1.12.dist-info/RECORD
