Metadata-Version: 2.4
Name: icoexpnet
Version: 0.1.12
Summary: iCoExpNet: gene co-expression network construction and analysis
Author-email: "Vlad V. Ungureanu" <vlad.ungureanu@york.ac.uk>
License-Expression: MIT
Project-URL: Homepage, https://github.com/vladUng/iCoExpNet
Project-URL: Documentation, https://github.com/vladUng/iCoExpNet#readme
Requires-Python: >=3.8
License-File: LICENSE
Requires-Dist: pandas
Requires-Dist: numpy
Requires-Dist: scipy
Requires-Dist: plotly
Requires-Dist: matplotlib
Requires-Dist: scikit-learn
Requires-Dist: igraph
Requires-Dist: leidenalg
Requires-Dist: lifelines
Requires-Dist: pyarrow
Requires-Dist: nbformat>=4.2.0
Dynamic: license-file
